{
  "MenuFile": "파일",
  "MenuFileOpen": "열기",
  "MenuFileSave": "저장",
  "MenuFileExtractAll": "전체 추출",
  "MenuFileExtractSelected": "추출 선택",
  "MenuFileImportHashtable": "해시 테이블 가져오기",
  "MenuFileCreate": "만들기",
  "MenuTools": "도구",
  "MenuToolsGenerateHashtable": "해시 테이블 생성",
  "MenuFilter": "필터",
  "DialogSettings": "설정",
  "SettingsInitialDialogPaths": "초기 다이얼로그 상자 경로",
  "SettingOpenWadDialogInitialDirectory": "WAD 다이얼로그 상자 초기 디렉토리 열기",
  "SettingSaveWadDialogInitialDirectory": "WAD 다이얼로그 상자 초기 디렉토리 저장",
  "SettingExtractWadDialogInitialDirectory": "WAD 다이얼로그 상자 초기 디렉토리 추출",
  "SettingOpenWadDialogInitialDirectoryDescription": "다이얼로그 상자가 시작될 폴더를 선택하십시오.",
  "SettingSaveWadDialogInitialDirectoryDescription": "다이얼로그 상자가 저장될 폴더를 선택하십시오.",
  "SettingExtractWadDialogInitialDirectoryDescription": "다이얼로그 상자가 추출될 폴더를 선택하십시오.",
  "SettingBINHashtableGeneration": "BIN 파일에서 해시 테이블 생성",
  "SettingCDragonHashSync": "CDragon과의 동기화 해시",
  "SettingLocalization": "현지화:",
  "DialogOK": "확인",
  "PreviewDescriptionDDS": "DDS 미리보기",
  "PreviewDescriptionSKN": "SKN 미리보기",
  "PreviewDescriptionStaticObject": "StaticObject 미리보기",
  "PreviewDescriptionMapGeometry": "MapGeometry 미리보기",
  "FatalErrorMessage": "오류가 발생했습니다. 이제 옵시디언을 종료합니다.",
  "FatalError": "옵시디언 - 치명적 오류",
  "DialogSyncHashesMessage": "해시 테이블 동기화 중...",
  "DialogSavingWadMessage": "저장 중",
  "DialogOpeningWadMessage": "여는 중",
  "DialogExtractWadPackedMappingMessage": "맵 파일 추출하기",
  "DialogExtractWadCreatingFoldersMessage": "폴더 만드는 중",
  "WadContextMenuAddFiles": "파일 추가",
  "WadContextMenuAddFolders": "폴더 추가",
  "WadContextMenuRemove": "제거",
  "WadContextMenuModifyData": "데이터 수정",
  "UpdateMessage": "새로운 버전의 Obsidian을 사용할 수 있습니다. 확인 버튼을 클릭하여 다운로드하십시오.",
  "OpeningHashtablesError": "옵시디언이 선택한 해시 테이블을 열 수 없습니다.",
  "OpeningWadError": "옵시디언이 선택한 WAD 파일을 열 수 없습니다.",
  "PreviewErrorDDS": "이 DDS 형식의 미리보기가 지원되지 않습니다.",
  "PreviewErrorGeneric": "선택한 파일을 미리 볼 수 없습니다.",
  "DragAndDropFileCountError": "옵시디언에 둘 이상의 WAD 파일을 놓을 수 없습니다.",
  "DialogDownloadingLocalizations": "현지화 다운로드 중..."
}